[{"id":"29075804","title":"Harry Potter and the Deathly Hallows","imageUrl":"https://images-na.ssl-images-amazon.com/images/I/51jyI6lYi1L._SX342_BO1,204,203,200_.jpg","price":"1000","description":"Nice bok "},{"id":"26901226","title":"Code Geass","imageUrl":"https://upload.wikimedia.org/wikipedia/en/7/74/Code_Geass_R1_box_set_cover.jpg","price":"2000","description":"Nice Manga"},{"id":"71476718","title":"Moomin","imageUrl":"https://lr-assets.storage.googleapis.com/kids/covers/_hires_imported/9780141329215.jpg","price":"3000","description":"Nice Cartoon"}]